flask_wxpay_plus/__init__.py
flask_wxpay_plus/utils.py
flask_wxpay_plus/wechatpay.py
Flask_WxPay_Plus-0.1.4.dist-info/METADATA
Flask_WxPay_Plus-0.1.4.dist-info/WHEEL
Flask_WxPay_Plus-0.1.4.dist-info/top_level.txt
Flask_WxPay_Plus-0.1.4.dist-info/RECORD
